multiagents/__init__.py
multiagents/cli.py
multiagents/llms.txt
multiagents/py.typed
multiagents/agents/multiagents-architect.md
multiagents/core/__init__.py
multiagents/core/exceptions.py
multiagents/core/factory.py
multiagents/core/saga_context.py
multiagents/event_bus/__init__.py
multiagents/event_bus/events.py
multiagents/event_bus/interface.py
multiagents/event_bus/redis_bus.py
multiagents/monitoring/__init__.py
multiagents/monitoring/config.py
multiagents/monitoring/event_monitor.py
multiagents/monitoring/interfaces.py
multiagents/monitoring/metrics_collector.py
multiagents/monitoring/worker_monitor.py
multiagents/monitoring/loggers/__init__.py
multiagents/monitoring/loggers/composite_logger.py
multiagents/monitoring/loggers/console_logger.py
multiagents/monitoring/loggers/file_logger.py
multiagents/orchestrator/__init__.py
multiagents/orchestrator/diagram_generator.py
multiagents/orchestrator/interface.py
multiagents/orchestrator/orchestrator.py
multiagents/orchestrator/workflow.py
multiagents/templates/basic/README.md
multiagents/templates/basic/main.py
multiagents/templates/basic/requirements.txt
multiagents/templates/basic/config/monitoring.yaml
multiagents/templates/basic/workers/__init__.py
multiagents/templates/basic/workers/basic_workers.py
multiagents/templates/dspy/README.md
multiagents/templates/dspy/requirements.txt
multiagents/templates/ecommerce/README.md
multiagents/templates/ecommerce/main.py
multiagents/worker_sdk/__init__.py
multiagents/worker_sdk/base_worker.py
multiagents/worker_sdk/decorators.py
multiagents/worker_sdk/dspy_modules.py
multiagents/worker_sdk/dspy_wrapper.py
multiagents/worker_sdk/interface.py
multiagents/worker_sdk/worker_manager.py
multiagents_framework-0.1.3.dist-info/licenses/LICENSE
multiagents_framework-0.1.3.dist-info/METADATA
multiagents_framework-0.1.3.dist-info/WHEEL
multiagents_framework-0.1.3.dist-info/entry_points.txt
multiagents_framework-0.1.3.dist-info/top_level.txt
multiagents_framework-0.1.3.dist-info/RECORD
