Metadata-Version: 2.4
Name: multiagents-framework
Version: 0.1.3
Summary: Hybrid Event-Driven Orchestration Framework
Home-page: https://github.com/xavierau/multiagents
Author: MultiAgents Team
Author-email: MultiAgents Team <info@multiagents.dev>
License: MIT
Project-URL: Homepage, https://github.com/xavierau/multiagents
Project-URL: Documentation, https://github.com/xavierau/multiagents/tree/main/docs
Project-URL: Repository, https://github.com/xavierau/multiagents
Project-URL: Issues, https://github.com/xavierau/multiagents/issues
Project-URL: Changelog, https://github.com/xavierau/multiagents/blob/main/CHANGELOG.md
Keywords: orchestration,workflow,event-driven,saga,dspy,llm,agents,conversational-ai,multi-agent
Classifier: Development Status :: 3 - Alpha
Classifier: Intended Audience :: Developers
Classifier: License :: OSI Approved :: MIT License
Classifier: Programming Language :: Python :: 3
Classifier: Programming Language :: Python :: 3.8
Classifier: Programming Language :: Python :: 3.9
Classifier: Programming Language :: Python :: 3.10
Classifier: Programming Language :: Python :: 3.11
Classifier: Programming Language :: Python :: 3.12
Classifier: Topic :: Software Development :: Libraries :: Python Modules
Classifier: Topic :: System :: Distributed Computing
Requires-Python: >=3.8
License-File: LICENSE
Requires-Dist: redis>=5.0.0
Requires-Dist: pydantic>=2.0.0
Requires-Dist: asyncio-redis>=0.16.0
Requires-Dist: dspy-ai>=2.0.0
Requires-Dist: structlog>=23.0.0
Requires-Dist: opentelemetry-api>=1.20.0
Requires-Dist: opentelemetry-sdk>=1.20.0
Requires-Dist: python-dotenv>=1.0.0
Requires-Dist: click>=8.0.0
Requires-Dist: rich>=13.0.0
Provides-Extra: dev
Requires-Dist: pytest>=7.0.0; extra == "dev"
Requires-Dist: pytest-cov>=4.0.0; extra == "dev"
Requires-Dist: pytest-asyncio>=0.21.0; extra == "dev"
Requires-Dist: black>=23.0.0; extra == "dev"
Requires-Dist: mypy>=1.0.0; extra == "dev"
Requires-Dist: ruff>=0.1.0; extra == "dev"
Requires-Dist: pre-commit>=3.0.0; extra == "dev"
Provides-Extra: docs
Requires-Dist: mkdocs>=1.5.0; extra == "docs"
Requires-Dist: mkdocs-material>=9.0.0; extra == "docs"
Requires-Dist: mkdocstrings[python]>=0.23.0; extra == "docs"
Provides-Extra: examples
Requires-Dist: openai>=1.0.0; extra == "examples"
Requires-Dist: anthropic>=0.7.0; extra == "examples"
Requires-Dist: jupyter>=1.0.0; extra == "examples"
Dynamic: author
Dynamic: home-page
Dynamic: license-file
Dynamic: requires-python
